usbbluetooth/__init__.py
usbbluetooth/controller.py
usbbluetooth/hci_hdr_type.py
usbbluetooth/list_controllers.py
usbbluetooth/exception/device_closed_exception.py
usbbluetooth/exception/insufficient_permissions_exception.py
usbbluetooth/exception/wrong_driver_exception.py
usbbluetooth-0.1.4.dist-info/METADATA
usbbluetooth-0.1.4.dist-info/WHEEL
usbbluetooth-0.1.4.dist-info/licenses/LICENSE.md
usbbluetooth-0.1.4.dist-info/RECORD
