Metadata-Version: 2.4
Name: usbbluetooth
Version: 0.1.4
Summary: Take full control of your USB Bluetooth controllers!
Project-URL: Homepage, https://usbbluetooth.github.io/
Project-URL: Bug Tracker, https://github.com/usbbluetooth/usbbluetooth-python/issues
Author-email: Antonio Vázquez Blanco <antoniovazquezblanco@gmail.com>
License: GPL-3.0-only
License-File: LICENSE.md
Keywords: bluetooth
Classifier: Intended Audience :: Developers
Classifier: Intended Audience :: Information Technology
Classifier: Intended Audience :: Science/Research
Classifier: Intended Audience :: System Administrators
Classifier: Intended Audience :: Telecommunications Industry
Classifier: License :: OSI Approved :: GNU General Public License v3 (GPLv3)
Classifier: Operating System :: OS Independent
Classifier: Programming Language :: Python :: 3
Classifier: Topic :: Security
Requires-Python: >=3.0
Requires-Dist: pyusb
